AUTHORS
LICENSE
README.rst
dev_requirements.txt
requirements.txt
setup.py
Ella_Tagging.egg-info/PKG-INFO
Ella_Tagging.egg-info/SOURCES.txt
Ella_Tagging.egg-info/dependency_links.txt
Ella_Tagging.egg-info/requires.txt
Ella_Tagging.egg-info/top_level.txt
ella_tagging/__init__.py
ella_tagging/newman_admin.py
ella_tagging/related_finders.py
ella_tagging/urls.py
ella_tagging/views.py
ella_tagging/locale/cs/LC_MESSAGES/django.mo
ella_tagging/locale/cs/LC_MESSAGES/django.po
setuptools_dummy-0.1.0.4-py2.7.egg/setuptools_dummy.py
setuptools_dummy-0.1.0.4-py2.7.egg/EGG-INFO/PKG-INFO
setuptools_dummy-0.1.0.4-py2.7.egg/EGG-INFO/SOURCES.txt
setuptools_dummy-0.1.0.4-py2.7.egg/EGG-INFO/dependency_links.txt
setuptools_dummy-0.1.0.4-py2.7.egg/EGG-INFO/entry_points.txt
setuptools_dummy-0.1.0.4-py2.7.egg/EGG-INFO/top_level.txt
setuptools_dummy-0.1.0.4-py2.7.egg/EGG-INFO/zip-safe
test_ella_tagging/__init__.py
test_ella_tagging/manage.py
test_ella_tagging/run_tests.py
test_ella_tagging/test_pagination.py
test_ella_tagging/test_related.py
test_ella_tagging/test_views.py
test_ella_tagging/urls.py
test_ella_tagging/settings/__init__.py
test_ella_tagging/settings/base.py
test_ella_tagging/settings/config.py